tyxonq/__init__.py
tyxonq/about.py
tyxonq/config.py
tyxonq/utils.py
tyxonq/waveforms.py
tyxonq/applications/__init__.py
tyxonq/applications/chem/__init__.py
tyxonq/applications/chem/constants.py
tyxonq/applications/chem/molecule.py
tyxonq/applications/chem/algorithms/__init__.py
tyxonq/applications/chem/algorithms/hea.py
tyxonq/applications/chem/algorithms/kupccgsd.py
tyxonq/applications/chem/algorithms/puccd.py
tyxonq/applications/chem/algorithms/ucc.py
tyxonq/applications/chem/algorithms/uccsd.py
tyxonq/applications/chem/chem_libs/circuit_chem_library/ansatz_kupccgsd.py
tyxonq/applications/chem/chem_libs/circuit_chem_library/ansatz_puccd.py
tyxonq/applications/chem/chem_libs/circuit_chem_library/ansatz_uccsd.py
tyxonq/applications/chem/chem_libs/hamiltonians_chem_library/__init__.py
tyxonq/applications/chem/chem_libs/hamiltonians_chem_library/hamiltonian_builders.py
tyxonq/applications/chem/chem_libs/hamiltonians_chem_library/pyrazine.py
tyxonq/applications/chem/chem_libs/hamiltonians_chem_library/sbm.py
tyxonq/applications/chem/chem_libs/quantum_chem_library/__init__.py
tyxonq/applications/chem/chem_libs/quantum_chem_library/ci_operator_tensors.py
tyxonq/applications/chem/chem_libs/quantum_chem_library/ci_state_mapping.py
tyxonq/applications/chem/chem_libs/quantum_chem_library/civector_ops.py
tyxonq/applications/chem/chem_libs/quantum_chem_library/pyscf_civector.py
tyxonq/applications/chem/chem_libs/quantum_chem_library/statevector_ops.py
tyxonq/applications/chem/runtimes/__init__.py
tyxonq/applications/chem/runtimes/dynamics_numeric.py
tyxonq/applications/chem/runtimes/hea_device_runtime.py
tyxonq/applications/chem/runtimes/hea_numeric_runtime.py
tyxonq/applications/chem/runtimes/ucc_device_runtime.py
tyxonq/applications/chem/runtimes/ucc_numeric_runtime.py
tyxonq/cloud/__init__.py
tyxonq/cloud/api.py
tyxonq/compiler/__init__.py
tyxonq/compiler/api.py
tyxonq/compiler/compile_engine/native/compile_plan.py
tyxonq/compiler/compile_engine/native/native_compiler.py
tyxonq-0.9.9.dist-info/licenses/LICENSE
tyxonq-0.9.9.dist-info/METADATA
tyxonq-0.9.9.dist-info/WHEEL
tyxonq-0.9.9.dist-info/top_level.txt
tyxonq-0.9.9.dist-info/RECORD
