Metadata-Version: 2.4
Name: tyxonq
Version: 0.9.9
Summary: Quantum computing framework with multi-backend support
Author-email: TyxonQ Development Team <code@quregenai.com>
License: Apache-2.0
Project-URL: Homepage, https://github.com/QureGenAI-Biotech/TyxonQ
Project-URL: Documentation, https://github.com/QureGenAI-Biotech/TyxonQ
Project-URL: Repository, https://github.com/QureGenAI-Biotech/TyxonQ
Project-URL: Issues, https://github.com/QureGenAI-Biotech/TyxonQ/issues
Project-URL: Official Website, https://www.tyxonq.com
Keywords: quantum,quantum-computing,quantum-machine-learning,quantum-chemistry,quantum-simulation
Classifier: Development Status :: 4 - Beta
Classifier: Intended Audience :: Science/Research
Classifier: Intended Audience :: Developers
Classifier: Topic :: Scientific/Engineering :: Physics
Classifier: Topic :: Scientific/Engineering :: Artificial Intelligence
Classifier: License :: OSI Approved :: Apache Software License
Classifier: Programming Language :: Python :: 3
Classifier: Programming Language :: Python :: 3.10
Classifier: Programming Language :: Python :: 3.11
Classifier: Programming Language :: Python :: 3.12
Classifier: Operating System :: OS Independent
Requires-Python: <3.13,>=3.10
License-File: LICENSE
Requires-Dist: cirq>=1.5.0
Requires-Dist: numpy>=2.0.2
Requires-Dist: opt-einsum>=3.4.0
Requires-Dist: python-dotenv>=1.1.1
Requires-Dist: qiskit>=2.1.0
Requires-Dist: requests>=2.32.4
Requires-Dist: ruff>=0.12.2
Requires-Dist: scipy>=1.13.1
Requires-Dist: symengine>=0.14.1
Requires-Dist: sympy>=1.14.0
Requires-Dist: torch>=2.7.1
Requires-Dist: torchvision>=0.22
Provides-Extra: dev
Requires-Dist: jupyter>=1.1.1; extra == "dev"
Requires-Dist: pytest>=6.0; extra == "dev"
Requires-Dist: pytest-lazy-fixtures>=1.1.4; extra == "dev"
Requires-Dist: build>=0.8.0; extra == "dev"
Requires-Dist: twine>=4.0.0; extra == "dev"
Dynamic: license-file
